config/__init__.py
config/auth.py
config/cf.py
config/cfenv.py
config/cloudfoundry.py
config/configserver3.py
config/core.py
config/spring.py
config_client3-2.0.0.dist-info/LICENSE
config_client3-2.0.0.dist-info/METADATA
config_client3-2.0.0.dist-info/WHEEL
config_client3-2.0.0.dist-info/top_level.txt
config_client3-2.0.0.dist-info/RECORD
