Metadata-Version: 2.1
Name: config-client3
Version: 2.0.0
Summary: config service client for pcf config-server3
Home-page: https://github.com/thedonutz/config-client
Author: Jeff M
Author-email: quicksh0t12@gmail.com
License: Apache-2.0
Project-URL: Documentation, https://github.com/thedonutz/config-client
Project-URL: Code, https://github.com/thedonutz/config-client
Project-URL: Issue tracker, https://github.com/thedonutz/config-client/issues
Platform: UNKNOWN
Classifier: Programming Language :: Python :: 3.6
Classifier: Programming Language :: Python :: 3.7
Classifier: Framework :: AsyncIO
Classifier: Framework :: Flask
Classifier: Development Status :: 5 - Production/Stable
Classifier: Intended Audience :: Developers
Classifier: License :: OSI Approved :: Apache Software License
Classifier: Operating System :: OS Independent
Classifier: Topic :: Software Development :: Libraries :: Java Libraries
Requires-Python: >=3.6.0
Requires-Dist: attrs (>=19.1.0)
Requires-Dist: glom (>=19.2.0)
Requires-Dist: requests (>=2.22.0)
